kueue/__init__.py
kueue/_types.py
kueue/config.py
kueue/consumer.py
kueue/task.py
kueue-0.1.2.dist-info/LICENSE
kueue-0.1.2.dist-info/WHEEL
kueue-0.1.2.dist-info/METADATA
kueue-0.1.2.dist-info/RECORD
