Metadata-Version: 2.1
Name: kueue
Version: 0.1.2
Summary: Distributed Task Queue - backed by Kafka
Home-page: https://github.com/jarojasm95/kueue
License: MIT
Keywords: python,kafka,distributed,task-queue
Author: Jose Rojas
Author-email: jose.rojas95@mail.com
Requires-Python: >=3.8,<4.0
Classifier: License :: OSI Approved :: MIT License
Classifier: Programming Language :: Python :: 3
Classifier: Programming Language :: Python :: 3.8
Classifier: Programming Language :: Python :: 3.9
Requires-Dist: confluent-kafka (>=1.5.0,<2.0.0)
Requires-Dist: pydantic (>=1.7.3,<2.0.0)
Requires-Dist: wrapt (>=1.12.1,<2.0.0)
Project-URL: Repository, https://github.com/jarojasm95/kueue
